quick_flask/__init__.py
quick_flask/content.py
quick_flask/create.py
quick_flask-1.0.2.dist-info/LICENSE
quick_flask-1.0.2.dist-info/METADATA
quick_flask-1.0.2.dist-info/WHEEL
quick_flask-1.0.2.dist-info/entry_points.txt
quick_flask-1.0.2.dist-info/top_level.txt
quick_flask-1.0.2.dist-info/RECORD
