Metadata-Version: 2.2
Name: quick-flask
Version: 1.0.2
Summary: CLI tool to quickly generate Flask apps
Home-page: https://github.com/adimail/quickflask
Author: Aditya Godse
Author-email: adimail2404@gmail.com
Project-URL: Bug Reports, https://github.com/adimail/quickflask/issues
Project-URL: Source, https://github.com/adimail/quickflask
Project-URL: Documentation, https://adimail.github.io/quickflask/
Keywords: flask,web development,cli tool
Classifier: Development Status :: 4 - Beta
Classifier: Intended Audience :: Developers
Classifier: Topic :: Software Development :: Build Tools
Classifier: Programming Language :: Python :: 3
Classifier: Programming Language :: Python :: 3.7
Classifier: Programming Language :: Python :: 3.8
Classifier: Programming Language :: Python :: 3.9
Classifier: License :: OSI Approved :: MIT License
Classifier: Operating System :: OS Independent
Requires-Python: >=3.7
License-File: LICENSE
Requires-Dist: click
Dynamic: author
Dynamic: author-email
Dynamic: classifier
Dynamic: description
Dynamic: description-content-type
Dynamic: home-page
Dynamic: keywords
Dynamic: project-url
Dynamic: requires-dist
Dynamic: requires-python
Dynamic: summary
